{
  "densidad": {
    "Den": "18.02"
  },
  "flujo": {
    "Ret": "0.0"
  },
  "nivel": {
    "NDepAl": "0",
    "NDepCa": "1343",
    "NDepfr": "228"
  },
  "potencia": {
    "PotCons": "104.0",
    "PotPlaca": "400.0",
    "PotPlaca_Est": "283.1",
    "VBat": "26.3"
  },
  "temperatura": {
    "TBat": "26.88",
    "TDepCa": "35.71",
    "TDepFr": "46.6",
    "TM": "26.75",
    "TR": "unknown",
    "TS": "26.0",
    "TSR1": "unknown",
    "TSR2": "unknown",
    "TSSR": "28.0",
    "TT": "27.25",
    "TTub": "28.16"
  }
}
