{
  "densidad": {
    "Den": "1.28"
  },
  "flujo": {
    "Ret": "2.9"
  },
  "nivel": {
    "NDepAl": "0",
    "NDepCa": "1376",
    "NDepfr": "228"
  },
  "potencia": {
    "PotCons": "86.0",
    "PotPlaca": "0.0",
    "PotPlaca_Est": "0.0",
    "VBat": "24.7"
  },
  "temperatura": {
    "TBat": "25.44",
    "TDepCa": "44.48",
    "TDepFr": "27.91",
    "TM": "26.75",
    "TR": "unknown",
    "TS": "25.25",
    "TSR1": "unknown",
    "TSR2": "unknown",
    "TSSR": "28.08",
    "TT": "27.25",
    "TTub": "41.75"
  }
}
