{
  "densidad": {
    "Den": "1.27"
  },
  "flujo": {
    "Ret": "2.0"
  },
  "nivel": {
    "NDepAl": "0",
    "NDepCa": "1371",
    "NDepfr": "228"
  },
  "potencia": {
    "PotCons": "1209.0",
    "PotPlaca": "1322.0",
    "PotPlaca_Est": "4143.75",
    "VBat": "27.0"
  },
  "temperatura": {
    "TBat": "27.31",
    "TDepCa": "44.97",
    "TDepFr": "66.05",
    "TM": "22.75",
    "TR": "unknown",
    "TS": "23.75",
    "TSR1": "unknown",
    "TSR2": "unknown",
    "TSSR": "25.17",
    "TT": "27.25",
    "TTub": "53.75"
  }
}
