{
  "densidad": {
    "Den": "18.02"
  },
  "flujo": {
    "Ret": "2.78"
  },
  "nivel": {
    "NDepAl": "0",
    "NDepCa": "1376",
    "NDepfr": "229"
  },
  "potencia": {
    "PotCons": "845.0",
    "PotPlaca": "1880.0",
    "PotPlaca_Est": "2923.99",
    "VBat": "28.8"
  },
  "temperatura": {
    "TBat": "28.81",
    "TDepCa": "52.77",
    "TDepFr": "85.0",
    "TM": "23.25",
    "TR": "unknown",
    "TS": "24.75",
    "TSR1": "unknown",
    "TSR2": "unknown",
    "TSSR": "26.25",
    "TT": "27.58",
    "TTub": "53.36"
  }
}
