{
  "densidad": {
    "Den": "18.02"
  },
  "flujo": {
    "Ret": "1.89"
  },
  "nivel": {
    "NDepAl": "0",
    "NDepCa": "1361",
    "NDepfr": "228"
  },
  "potencia": {
    "PotCons": "445.0",
    "PotPlaca": "567.0",
    "PotPlaca_Est": "168.11",
    "VBat": "27.0"
  },
  "temperatura": {
    "TBat": "31.19",
    "TDepCa": "39.39",
    "TDepFr": "67.36",
    "TM": "22.75",
    "TR": "unknown",
    "TS": "25.25",
    "TSR1": "unknown",
    "TSR2": "unknown",
    "TSSR": "24.5",
    "TT": "28.25",
    "TTub": "62.42"
  }
}
