{
  "densidad": {
    "Den": "1.28"
  },
  "flujo": {
    "Ret": "unknown"
  },
  "nivel": {
    "NDepAl": "unknown",
    "NDepCa": "unknown",
    "NDepfr": "unknown"
  },
  "potencia": {
    "PotCons": "694.0",
    "PotPlaca": "768.0",
    "PotPlaca_Est": "2663.74",
    "VBat": "27.0"
  },
  "temperatura": {
    "TBat": "25.25",
    "TDepCa": "unknown",
    "TDepFr": "unknown",
    "TM": "21.5",
    "TR": "unknown",
    "TS": "22.0",
    "TSR1": "unknown",
    "TSR2": "unknown",
    "TSSR": "23.75",
    "TT": "26.08",
    "TTub": "unknown"
  }
}
