{
  "densidad": {
    "Den": "18.02"
  },
  "flujo": {
    "Ret": "2.9"
  },
  "nivel": {
    "NDepAl": "0",
    "NDepCa": "1352",
    "NDepfr": "229"
  },
  "potencia": {
    "PotCons": "89.0",
    "PotPlaca": "131.0",
    "PotPlaca_Est": "100.07",
    "VBat": "25.1"
  },
  "temperatura": {
    "TBat": "25.31",
    "TDepCa": "36.82",
    "TDepFr": "36.72",
    "TM": "25.83",
    "TR": "unknown",
    "TS": "24.92",
    "TSR1": "unknown",
    "TSR2": "unknown",
    "TSSR": "27.25",
    "TT": "26.5",
    "TTub": "32.02"
  }
}
