{
  "densidad": {
    "Den": "1.27"
  },
  "flujo": {
    "Ret": "unknown"
  },
  "nivel": {
    "NDepAl": "unknown",
    "NDepCa": "unknown",
    "NDepfr": "unknown"
  },
  "potencia": {
    "PotCons": "140.0",
    "PotPlaca": "130.0",
    "PotPlaca_Est": "197.16",
    "VBat": "25.0"
  },
  "temperatura": {
    "TBat": "20.56",
    "TDepCa": "unknown",
    "TDepFr": "unknown",
    "TM": "22.5",
    "TR": "unknown",
    "TS": "20.5",
    "TSR1": "unknown",
    "TSR2": "unknown",
    "TSSR": "23.67",
    "TT": "22.58",
    "TTub": "unknown"
  }
}
