{
  "densidad": {
    "Den": "1.28"
  },
  "flujo": {
    "Ret": "0.0"
  },
  "nivel": {
    "NDepAl": "0",
    "NDepCa": "1371",
    "NDepfr": "228"
  },
  "potencia": {
    "PotCons": "81.0",
    "PotPlaca": "3.0",
    "PotPlaca_Est": "0.0",
    "VBat": "25.5"
  },
  "temperatura": {
    "TBat": "28.69",
    "TDepCa": "37.84",
    "TDepFr": "29.71",
    "TM": "24.5",
    "TR": "unknown",
    "TS": "24.75",
    "TSR1": "unknown",
    "TSR2": "unknown",
    "TSSR": "25.25",
    "TT": "27.33",
    "TTub": "46.17"
  }
}
