{
  "densidad": {
    "Den": "1.27"
  },
  "flujo": {
    "Ret": "2.04"
  },
  "nivel": {
    "NDepAl": "--",
    "NDepCa": "1375",
    "NDepfr": "229"
  },
  "potencia": {
    "PotCons": "92.0",
    "PotPlaca": "779.0",
    "PotPlaca_Est": "406.61",
    "VBat": "27.1"
  },
  "temperatura": {
    "TBat": "24.62",
    "TDepCa": "39.62",
    "TDepFr": "--",
    "TM": "25.92",
    "TR": "unknown",
    "TS": "24.25",
    "TSR1": "unknown",
    "TSR2": "unknown",
    "TSSR": "27.25",
    "TT": "26.25",
    "TTub": "--"
  }
}
