{
  "densidad": {
    "Den": "18.02"
  },
  "flujo": {
    "Ret": "2.05"
  },
  "nivel": {
    "NDepAl": "0",
    "NDepCa": "1359",
    "NDepfr": "228"
  },
  "potencia": {
    "PotCons": "1085.0",
    "PotPlaca": "1181.0",
    "PotPlaca_Est": "3887.34",
    "VBat": "27.0"
  },
  "temperatura": {
    "TBat": "30.69",
    "TDepCa": "54.02",
    "TDepFr": "49.12",
    "TM": "21.58",
    "TR": "unknown",
    "TS": "24.5",
    "TSR1": "unknown",
    "TSR2": "unknown",
    "TSSR": "24.25",
    "TT": "28.25",
    "TTub": "77.4"
  }
}
