{
  "densidad": {
    "Den": "1.28"
  },
  "flujo": {
    "Ret": "2.01"
  },
  "nivel": {
    "NDepAl": "0",
    "NDepCa": "1375",
    "NDepfr": "229"
  },
  "potencia": {
    "PotCons": "976.0",
    "PotPlaca": "1377.0",
    "PotPlaca_Est": "3719.1",
    "VBat": "28.8"
  },
  "temperatura": {
    "TBat": "26.5",
    "TDepCa": "45.61",
    "TDepFr": "75.48",
    "TM": "23.58",
    "TR": "unknown",
    "TS": "23.92",
    "TSR1": "unknown",
    "TSR2": "unknown",
    "TSSR": "25.92",
    "TT": "27.33",
    "TTub": "69.61"
  }
}
