{
  "densidad": {
    "Den": "18.02"
  },
  "flujo": {
    "Ret": "2.86"
  },
  "nivel": {
    "NDepAl": "0",
    "NDepCa": "1330",
    "NDepfr": "229"
  },
  "potencia": {
    "PotCons": "77.0",
    "PotPlaca": "0.0",
    "PotPlaca_Est": "0.0",
    "VBat": "24.8"
  },
  "temperatura": {
    "TBat": "27.5",
    "TDepCa": "38.62",
    "TDepFr": "48.25",
    "TM": "27.5",
    "TR": "unknown",
    "TS": "27.0",
    "TSR1": "unknown",
    "TSR2": "unknown",
    "TSSR": "29.08",
    "TT": "28.5",
    "TTub": "32.61"
  }
}
