{
  "densidad": {
    "Den": "18.02"
  },
  "flujo": {
    "Ret": "2.01"
  },
  "nivel": {
    "NDepAl": "0",
    "NDepCa": "1372",
    "NDepfr": "229"
  },
  "potencia": {
    "PotCons": "986.0",
    "PotPlaca": "1127.0",
    "PotPlaca_Est": "4065.86",
    "VBat": "27.0"
  },
  "temperatura": {
    "TBat": "28.44",
    "TDepCa": "46.32",
    "TDepFr": "57.61",
    "TM": "21.58",
    "TR": "unknown",
    "TS": "23.83",
    "TSR1": "unknown",
    "TSR2": "unknown",
    "TSSR": "24.08",
    "TT": "27.0",
    "TTub": "85.0"
  }
}
