{
  "densidad": {
    "Den": "18.02"
  },
  "flujo": {
    "Ret": "2.1"
  },
  "nivel": {
    "NDepAl": "0",
    "NDepCa": "1372",
    "NDepfr": "228"
  },
  "potencia": {
    "PotCons": "1051.0",
    "PotPlaca": "1201.0",
    "PotPlaca_Est": "4266.01",
    "VBat": "27.1"
  },
  "temperatura": {
    "TBat": "29.5",
    "TDepCa": "0.0",
    "TDepFr": "85.33",
    "TM": "22.75",
    "TR": "unknown",
    "TS": "24.25",
    "TSR1": "unknown",
    "TSR2": "unknown",
    "TSSR": "25.0",
    "TT": "28.25",
    "TTub": "0.0"
  }
}
