{
  "densidad": {
    "Den": "18.02"
  },
  "flujo": {
    "Ret": "1.38"
  },
  "nivel": {
    "NDepAl": "0",
    "NDepCa": "1372",
    "NDepfr": "228"
  },
  "potencia": {
    "PotCons": "1169.0",
    "PotPlaca": "1590.0",
    "PotPlaca_Est": "3819.18",
    "VBat": "28.8"
  },
  "temperatura": {
    "TBat": "29.81",
    "TDepCa": "61.09",
    "TDepFr": "57.23",
    "TM": "21.75",
    "TR": "unknown",
    "TS": "24.5",
    "TSR1": "unknown",
    "TSR2": "unknown",
    "TSSR": "24.5",
    "TT": "27.67",
    "TTub": "61.89"
  }
}
