{
  "densidad": {
    "Den": "18.02"
  },
  "flujo": {
    "Ret": "2.07"
  },
  "nivel": {
    "NDepAl": "0",
    "NDepCa": "1375",
    "NDepfr": "229"
  },
  "potencia": {
    "PotCons": "880.0",
    "PotPlaca": "1947.0",
    "PotPlaca_Est": "1361.09",
    "VBat": "27.8"
  },
  "temperatura": {
    "TBat": "26.75",
    "TDepCa": "37.15",
    "TDepFr": "36.94",
    "TM": "24.0",
    "TR": "unknown",
    "TS": "24.75",
    "TSR1": "unknown",
    "TSR2": "unknown",
    "TSSR": "27.0",
    "TT": "27.17",
    "TTub": "61.09"
  }
}
