{
  "densidad": {
    "Den": "18.02"
  },
  "flujo": {
    "Ret": "0.0"
  },
  "nivel": {
    "NDepAl": "0",
    "NDepCa": "1331",
    "NDepfr": "229"
  },
  "potencia": {
    "PotCons": "83.0",
    "PotPlaca": "0.0",
    "PotPlaca_Est": "0.0",
    "VBat": "24.7"
  },
  "temperatura": {
    "TBat": "27.19",
    "TDepCa": "37.91",
    "TDepFr": "47.74",
    "TM": "27.75",
    "TR": "unknown",
    "TS": "27.08",
    "TSR1": "unknown",
    "TSR2": "unknown",
    "TSSR": "29.08",
    "TT": "28.5",
    "TTub": "32.85"
  }
}
