{
  "densidad": {
    "Den": "18.02"
  },
  "flujo": {
    "Ret": "2.04"
  },
  "nivel": {
    "NDepAl": "0",
    "NDepCa": "1373",
    "NDepfr": "228"
  },
  "potencia": {
    "PotCons": "1943.0",
    "PotPlaca": "1977.0",
    "PotPlaca_Est": "4187.03",
    "VBat": "27.2"
  },
  "temperatura": {
    "TBat": "29.5",
    "TDepCa": "47.19",
    "TDepFr": "57.48",
    "TM": "21.33",
    "TR": "unknown",
    "TS": "23.75",
    "TSR1": "unknown",
    "TSR2": "unknown",
    "TSSR": "23.83",
    "TT": "27.75",
    "TTub": "70.34"
  }
}
