{
  "densidad": {
    "Den": "18.02"
  },
  "flujo": {
    "Ret": "2.91"
  },
  "nivel": {
    "NDepAl": "0",
    "NDepCa": "1321",
    "NDepfr": "228"
  },
  "potencia": {
    "PotCons": "90.0",
    "PotPlaca": "0.0",
    "PotPlaca_Est": "0.0",
    "VBat": "24.7"
  },
  "temperatura": {
    "TBat": "26.25",
    "TDepCa": "45.94",
    "TDepFr": "47.52",
    "TM": "26.5",
    "TR": "unknown",
    "TS": "26.25",
    "TSR1": "unknown",
    "TSR2": "unknown",
    "TSSR": "28.5",
    "TT": "27.67",
    "TTub": "41.65"
  }
}
