{
  "densidad": {
    "Den": "1.27"
  },
  "flujo": {
    "Ret": "2.05"
  },
  "nivel": {
    "NDepAl": "0",
    "NDepCa": "1375",
    "NDepfr": "228"
  },
  "potencia": {
    "PotCons": "582.0",
    "PotPlaca": "1824.0",
    "PotPlaca_Est": "1686.83",
    "VBat": "28.8"
  },
  "temperatura": {
    "TBat": "26.19",
    "TDepCa": "60.31",
    "TDepFr": "27.21",
    "TM": "25.25",
    "TR": "unknown",
    "TS": "25.25",
    "TSR1": "unknown",
    "TSR2": "unknown",
    "TSSR": "27.5",
    "TT": "27.42",
    "TTub": "68.73"
  }
}
