{
  "densidad": {
    "Den": "18.02"
  },
  "flujo": {
    "Ret": "2.04"
  },
  "nivel": {
    "NDepAl": "0",
    "NDepCa": "1360",
    "NDepfr": "228"
  },
  "potencia": {
    "PotCons": "1079.0",
    "PotPlaca": "1227.0",
    "PotPlaca_Est": "3862.84",
    "VBat": "27.0"
  },
  "temperatura": {
    "TBat": "30.69",
    "TDepCa": "54.02",
    "TDepFr": "49.12",
    "TM": "21.5",
    "TR": "unknown",
    "TS": "24.42",
    "TSR1": "unknown",
    "TSR2": "unknown",
    "TSSR": "24.25",
    "TT": "28.25",
    "TTub": "85.0"
  }
}
