{
  "densidad": {
    "Den": "1.27"
  },
  "flujo": {
    "Ret": "unknown"
  },
  "nivel": {
    "NDepAl": "unknown",
    "NDepCa": "unknown",
    "NDepfr": "unknown"
  },
  "potencia": {
    "PotCons": "114.0",
    "PotPlaca": "204.0",
    "PotPlaca_Est": "188.72",
    "VBat": "25.2"
  },
  "temperatura": {
    "TBat": "21.38",
    "TDepCa": "unknown",
    "TDepFr": "unknown",
    "TM": "22.67",
    "TR": "unknown",
    "TS": "21.0",
    "TSR1": "unknown",
    "TSR2": "unknown",
    "TSSR": "23.83",
    "TT": "22.75",
    "TTub": "unknown"
  }
}
