{
  "densidad": {
    "Den": "18.02"
  },
  "flujo": {
    "Ret": "2.06"
  },
  "nivel": {
    "NDepAl": "0",
    "NDepCa": "1361",
    "NDepfr": "229"
  },
  "potencia": {
    "PotCons": "1093.0",
    "PotPlaca": "1158.0",
    "PotPlaca_Est": "3577.14",
    "VBat": "27.0"
  },
  "temperatura": {
    "TBat": "30.31",
    "TDepCa": "0.0",
    "TDepFr": "0.0",
    "TM": "23.58",
    "TR": "unknown",
    "TS": "24.75",
    "TSR1": "unknown",
    "TSR2": "unknown",
    "TSSR": "25.0",
    "TT": "28.75",
    "TTub": "0.0"
  }
}
