{
  "densidad": {
    "Den": "18.02"
  },
  "flujo": {
    "Ret": "2.07"
  },
  "nivel": {
    "NDepAl": "0",
    "NDepCa": "1376",
    "NDepfr": "229"
  },
  "potencia": {
    "PotCons": "1173.0",
    "PotPlaca": "1285.0",
    "PotPlaca_Est": "3937.65",
    "VBat": "27.0"
  },
  "temperatura": {
    "TBat": "29.0",
    "TDepCa": "52.53",
    "TDepFr": "85.0",
    "TM": "22.0",
    "TR": "unknown",
    "TS": "24.75",
    "TSR1": "unknown",
    "TSR2": "unknown",
    "TSSR": "24.92",
    "TT": "27.5",
    "TTub": "69.26"
  }
}
