{
  "densidad": {
    "Den": "18.02"
  },
  "flujo": {
    "Ret": "2.07"
  },
  "nivel": {
    "NDepAl": "0",
    "NDepCa": "1370",
    "NDepfr": "229"
  },
  "potencia": {
    "PotCons": "1594.0",
    "PotPlaca": "1751.0",
    "PotPlaca_Est": "4447.77",
    "VBat": "27.0"
  },
  "temperatura": {
    "TBat": "29.25",
    "TDepCa": "53.86",
    "TDepFr": "38.28",
    "TM": "23.0",
    "TR": "unknown",
    "TS": "24.25",
    "TSR1": "unknown",
    "TSR2": "unknown",
    "TSSR": "25.0",
    "TT": "28.25",
    "TTub": "85.0"
  }
}
