{
  "densidad": {
    "Den": "18.02"
  },
  "flujo": {
    "Ret": "2.0"
  },
  "nivel": {
    "NDepAl": "0",
    "NDepCa": "1376",
    "NDepfr": "229"
  },
  "potencia": {
    "PotCons": "995.0",
    "PotPlaca": "2166.0",
    "PotPlaca_Est": "2562.79",
    "VBat": "28.8"
  },
  "temperatura": {
    "TBat": "28.94",
    "TDepCa": "0.0",
    "TDepFr": "0.0",
    "TM": "25.25",
    "TR": "unknown",
    "TS": "25.92",
    "TSR1": "unknown",
    "TSR2": "unknown",
    "TSSR": "28.0",
    "TT": "29.5",
    "TTub": "0.0"
  }
}
