{
  "densidad": {
    "Den": "18.02"
  },
  "flujo": {
    "Ret": "1.97"
  },
  "nivel": {
    "NDepAl": "0",
    "NDepCa": "1365",
    "NDepfr": "228"
  },
  "potencia": {
    "PotCons": "734.0",
    "PotPlaca": "776.0",
    "PotPlaca_Est": "222.32",
    "VBat": "26.1"
  },
  "temperatura": {
    "TBat": "30.81",
    "TDepCa": "39.25",
    "TDepFr": "40.7",
    "TM": "23.0",
    "TR": "unknown",
    "TS": "24.25",
    "TSR1": "unknown",
    "TSR2": "unknown",
    "TSSR": "25.0",
    "TT": "28.25",
    "TTub": "62.17"
  }
}
