{
  "densidad": {
    "Den": "18.02"
  },
  "flujo": {
    "Ret": "3.01"
  },
  "nivel": {
    "NDepAl": "0",
    "NDepCa": "1309",
    "NDepfr": "222"
  },
  "potencia": {
    "PotCons": "64.0",
    "PotPlaca": "663.0",
    "PotPlaca_Est": "234.3",
    "VBat": "26.9"
  },
  "temperatura": {
    "TBat": "28.19",
    "TDepCa": "0.0",
    "TDepFr": "0.0",
    "TM": "29.0",
    "TR": "unknown",
    "TS": "28.0",
    "TSR1": "unknown",
    "TSR2": "unknown",
    "TSSR": "29.5",
    "TT": "29.92",
    "TTub": "0.0"
  }
}
