{
  "densidad": {
    "Den": "18.02"
  },
  "flujo": {
    "Ret": "2.2"
  },
  "nivel": {
    "NDepAl": "0",
    "NDepCa": "1373",
    "NDepfr": "229"
  },
  "potencia": {
    "PotCons": "1183.0",
    "PotPlaca": "1362.0",
    "PotPlaca_Est": "4148.62",
    "VBat": "27.0"
  },
  "temperatura": {
    "TBat": "29.56",
    "TDepCa": "39.7",
    "TDepFr": "75.95",
    "TM": "21.5",
    "TR": "unknown",
    "TS": "23.75",
    "TSR1": "unknown",
    "TSR2": "unknown",
    "TSSR": "23.83",
    "TT": "28.0",
    "TTub": "55.68"
  }
}
