{
  "densidad": {
    "Den": "18.02"
  },
  "flujo": {
    "Ret": "2.47"
  },
  "nivel": {
    "NDepAl": "0",
    "NDepCa": "1369",
    "NDepfr": "229"
  },
  "potencia": {
    "PotCons": "793.0",
    "PotPlaca": "2117.0",
    "PotPlaca_Est": "1773.28",
    "VBat": "28.8"
  },
  "temperatura": {
    "TBat": "27.44",
    "TDepCa": "43.84",
    "TDepFr": "85.0",
    "TM": "26.0",
    "TR": "unknown",
    "TS": "26.75",
    "TSR1": "unknown",
    "TSR2": "unknown",
    "TSSR": "28.5",
    "TT": "28.5",
    "TTub": "68.56"
  }
}
