{
  "densidad": {
    "Den": "1.28"
  },
  "flujo": {
    "Ret": "1.76"
  },
  "nivel": {
    "NDepAl": "1",
    "NDepCa": "1375",
    "NDepfr": "229"
  },
  "potencia": {
    "PotCons": "860.0",
    "PotPlaca": "1164.0",
    "PotPlaca_Est": "3794.83",
    "VBat": "28.8"
  },
  "temperatura": {
    "TBat": "26.31",
    "TDepCa": "38.79",
    "TDepFr": "85.0",
    "TM": "23.75",
    "TR": "unknown",
    "TS": "23.25",
    "TSR1": "unknown",
    "TSR2": "unknown",
    "TSSR": "25.5",
    "TT": "27.25",
    "TTub": "85.0"
  }
}
