{
  "densidad": {
    "Den": "1.28"
  },
  "flujo": {
    "Ret": "unknown"
  },
  "nivel": {
    "NDepAl": "unknown",
    "NDepCa": "unknown",
    "NDepfr": "unknown"
  },
  "potencia": {
    "PotCons": "171.0",
    "PotPlaca": "1701.0",
    "PotPlaca_Est": "1274.9",
    "VBat": "28.8"
  },
  "temperatura": {
    "TBat": "22.69",
    "TDepCa": "unknown",
    "TDepFr": "unknown",
    "TM": "24.0",
    "TR": "unknown",
    "TS": "22.5",
    "TSR1": "unknown",
    "TSR2": "unknown",
    "TSSR": "25.5",
    "TT": "24.5",
    "TTub": "unknown"
  }
}
