{
  "densidad": {
    "Den": "1.28"
  },
  "flujo": {
    "Ret": "unknown"
  },
  "nivel": {
    "NDepAl": "unknown",
    "NDepCa": "unknown",
    "nDepfr": "unknown"
  },
  "potencia": {
    "PotCons": 484,
    "PotPlaca": "563",
    "PotPlaca_Est": 4241.7,
    "VBat": 27
  },
  "temperatura": {
    "TBat": "23.44",
    "TDepCa": "unknown",
    "TDepFr": "unknown",
    "TM": "20.75",
    "TR": "23.92",
    "TS": "20.75",
    "TSR1": "unknown",
    "TSR2": "unknown",
    "TSSR": "22.5",
    "TTub": "unknown"
  }
}
