{
  "densidad": {
    "Den": "18.02"
  },
  "flujo": {
    "Ret": "2.94"
  },
  "nivel": {
    "NDepAl": "0",
    "NDepCa": "1309",
    "NDepfr": "229"
  },
  "potencia": {
    "PotCons": "110.0",
    "PotPlaca": "1100.0",
    "PotPlaca_Est": "511.85",
    "VBat": "27.7"
  },
  "temperatura": {
    "TBat": "28.06",
    "TDepCa": "29.64",
    "TDepFr": "13.88",
    "TM": "28.67",
    "TR": "unknown",
    "TS": "27.5",
    "TSR1": "unknown",
    "TSR2": "unknown",
    "TSSR": "29.0",
    "TT": "29.5",
    "TTub": "4.28"
  }
}
