{
  "densidad": {
    "Den": "1.28"
  },
  "flujo": {
    "Ret": "2.05"
  },
  "nivel": {
    "NDepAl": "0",
    "NDepCa": "1369",
    "NDepfr": "229"
  },
  "potencia": {
    "PotCons": "1167.0",
    "PotPlaca": "1278.0",
    "PotPlaca_Est": "1035.73",
    "VBat": "27.0"
  },
  "temperatura": {
    "TBat": "29.0",
    "TDepCa": "37.61",
    "TDepFr": "75.78",
    "TM": "21.0",
    "TR": "unknown",
    "TS": "23.83",
    "TSR1": "unknown",
    "TSR2": "unknown",
    "TSSR": "23.75",
    "TT": "26.83",
    "TTub": "69.42"
  }
}
