{
  "densidad": {
    "Den": "1.28"
  },
  "flujo": {
    "Ret": "2.04"
  },
  "nivel": {
    "NDepAl": "0",
    "NDepCa": "1374",
    "NDepfr": "228"
  },
  "potencia": {
    "PotCons": "683.0",
    "PotPlaca": "689.0",
    "PotPlaca_Est": "194.4",
    "VBat": "25.8"
  },
  "temperatura": {
    "TBat": "29.0",
    "TDepCa": "55.02",
    "TDepFr": "48.34",
    "TM": "22.5",
    "TR": "unknown",
    "TS": "23.25",
    "TSR1": "unknown",
    "TSR2": "unknown",
    "TSSR": "23.92",
    "TT": "27.25",
    "TTub": "70.12"
  }
}
