{
  "densidad": {
    "Den": "1.27"
  },
  "flujo": {
    "Ret": "unknown"
  },
  "nivel": {
    "NDepAl": "unknown",
    "NDepCa": "unknown",
    "NDepfr": "unknown"
  },
  "potencia": {
    "PotCons": "121.0",
    "PotPlaca": "1556.0",
    "PotPlaca_Est": "999.81",
    "VBat": "28.5"
  },
  "temperatura": {
    "TBat": "22.12",
    "TDepCa": "unknown",
    "TDepFr": "unknown",
    "TM": "23.75",
    "TR": "unknown",
    "TS": "21.75",
    "TSR1": "unknown",
    "TSR2": "unknown",
    "TSSR": "24.83",
    "TT": "24.0",
    "TTub": "unknown"
  }
}
