{
  "densidad": {
    "Den": "18.02"
  },
  "flujo": {
    "Ret": "2.07"
  },
  "nivel": {
    "NDepAl": "0",
    "NDepCa": "1375",
    "NDepfr": "229"
  },
  "potencia": {
    "PotCons": "943.0",
    "PotPlaca": "1975.0",
    "PotPlaca_Est": "1382.21",
    "VBat": "27.7"
  },
  "temperatura": {
    "TBat": "26.75",
    "TDepCa": "37.15",
    "TDepFr": "36.94",
    "TM": "24.0",
    "TR": "unknown",
    "TS": "24.75",
    "TSR1": "unknown",
    "TSR2": "unknown",
    "TSSR": "26.92",
    "TT": "27.0",
    "TTub": "61.09"
  }
}
