{
  "densidad": {
    "Den": "1.27"
  },
  "flujo": {
    "Ret": "1.95"
  },
  "nivel": {
    "NDepAl": "0",
    "NDepCa": "1376",
    "NDepfr": "229"
  },
  "potencia": {
    "PotCons": "1626.0",
    "PotPlaca": "2980.0",
    "PotPlaca_Est": "4058.28",
    "VBat": "27.3"
  },
  "temperatura": {
    "TBat": "29.38",
    "TDepCa": "53.4",
    "TDepFr": "48.15",
    "TM": "23.75",
    "TR": "unknown",
    "TS": "24.5",
    "TSR1": "unknown",
    "TSR2": "unknown",
    "TSSR": "25.25",
    "TT": "28.5",
    "TTub": "62.01"
  }
}
