{
  "densidad": {
    "Den": "18.02"
  },
  "flujo": {
    "Ret": "2.01"
  },
  "nivel": {
    "NDepAl": "0",
    "NDepCa": "1376",
    "NDepfr": "228"
  },
  "potencia": {
    "PotCons": "930.0",
    "PotPlaca": "1832.0",
    "PotPlaca_Est": "1252.79",
    "VBat": "27.7"
  },
  "temperatura": {
    "TBat": "28.75",
    "TDepCa": "37.43",
    "TDepFr": "47.51",
    "TM": "26.25",
    "TR": "unknown",
    "TS": "27.0",
    "TSR1": "unknown",
    "TSR2": "unknown",
    "TSSR": "29.5",
    "TT": "30.0",
    "TTub": "37.52"
  }
}
