{
  "densidad": {
    "Den": "1.27"
  },
  "flujo": {
    "Ret": "unknown"
  },
  "nivel": {
    "NDepAl": "unknown",
    "NDepCa": "unknown",
    "NDepfr": "unknown"
  },
  "potencia": {
    "PotCons": "815.0",
    "PotPlaca": "950.0",
    "PotPlaca_Est": "1997.8",
    "VBat": "27.0"
  },
  "temperatura": {
    "TBat": "26.06",
    "TDepCa": "unknown",
    "TDepFr": "unknown",
    "TM": "22.75",
    "TR": "unknown",
    "TS": "22.5",
    "TSR1": "unknown",
    "TSR2": "unknown",
    "TSSR": "24.5",
    "TT": "26.67",
    "TTub": "unknown"
  }
}
