{
  "densidad": {
    "Den": "1.27"
  },
  "flujo": {
    "Ret": "2.06"
  },
  "nivel": {
    "NDepAl": "229",
    "NDepCa": "229",
    "NDepfr": "228"
  },
  "potencia": {
    "PotCons": "865.0",
    "PotPlaca": "979.0",
    "PotPlaca_Est": "648.24",
    "VBat": "27.0"
  },
  "temperatura": {
    "TBat": "26.62",
    "TDepCa": "--",
    "TDepFr": "--",
    "TM": "22.25",
    "TR": "unknown",
    "TS": "22.5",
    "TSR1": "unknown",
    "TSR2": "unknown",
    "TSSR": "24.0",
    "TT": "26.25",
    "TTub": "--"
  }
}
