{
  "densidad": {
    "Den": "18.02"
  },
  "flujo": {
    "Ret": "2.03"
  },
  "nivel": {
    "NDepAl": "0",
    "NDepCa": "1375",
    "NDepfr": "228"
  },
  "potencia": {
    "PotCons": "450.0",
    "PotPlaca": "539.0",
    "PotPlaca_Est": "108.73",
    "VBat": "26.6"
  },
  "temperatura": {
    "TBat": "31.12",
    "TDepCa": "0.0",
    "TDepFr": "0.0",
    "TM": "23.0",
    "TR": "unknown",
    "TS": "24.5",
    "TSR1": "unknown",
    "TSR2": "unknown",
    "TSSR": "24.25",
    "TT": "28.0",
    "TTub": "0.0"
  }
}
