{
  "densidad": {
    "Den": "1.27"
  },
  "flujo": {
    "Ret": "2.96"
  },
  "nivel": {
    "NDepAl": "0",
    "NDepCa": "1375",
    "NDepfr": "228"
  },
  "potencia": {
    "PotCons": "126.0",
    "PotPlaca": "850.0",
    "PotPlaca_Est": "511.55",
    "VBat": "27.1"
  },
  "temperatura": {
    "TBat": "25.81",
    "TDepCa": "52.77",
    "TDepFr": "27.53",
    "TM": "27.0",
    "TR": "unknown",
    "TS": "25.58",
    "TSR1": "unknown",
    "TSR2": "unknown",
    "TSSR": "28.25",
    "TT": "27.5",
    "TTub": "50.77"
  }
}
