{
  "densidad": {
    "Den": "1.28"
  },
  "flujo": {
    "Ret": "1.63"
  },
  "nivel": {
    "NDepAl": "0",
    "NDepCa": "1369",
    "NDepfr": "229"
  },
  "potencia": {
    "PotCons": "1210.0",
    "PotPlaca": "1354.0",
    "PotPlaca_Est": "2003.11",
    "VBat": "27.0"
  },
  "temperatura": {
    "TBat": "30.31",
    "TDepCa": "37.94",
    "TDepFr": "75.92",
    "TM": "21.75",
    "TR": "unknown",
    "TS": "24.25",
    "TSR1": "unknown",
    "TSR2": "unknown",
    "TSSR": "24.0",
    "TT": "27.25",
    "TTub": "85.0"
  }
}
