{
  "densidad": {
    "Den": "18.02"
  },
  "flujo": {
    "Ret": "2.04"
  },
  "nivel": {
    "NDepAl": "0",
    "NDepCa": "1365",
    "NDepfr": "229"
  },
  "potencia": {
    "PotCons": "985.0",
    "PotPlaca": "2368.0",
    "PotPlaca_Est": "2547.61",
    "VBat": "28.8"
  },
  "temperatura": {
    "TBat": "28.5",
    "TDepCa": "0.0",
    "TDepFr": "0.0",
    "TM": "24.75",
    "TR": "unknown",
    "TS": "24.83",
    "TSR1": "unknown",
    "TSR2": "unknown",
    "TSSR": "27.08",
    "TT": "28.75",
    "TTub": "0.0"
  }
}
