{
  "densidad": {
    "Den": "1.27"
  },
  "flujo": {
    "Ret": "0.0"
  },
  "nivel": {
    "NDepAl": "0",
    "NDepCa": "1372",
    "NDepfr": "229"
  },
  "potencia": {
    "PotCons": "116.0",
    "PotPlaca": "329.0",
    "PotPlaca_Est": "207.52",
    "VBat": "26.3"
  },
  "temperatura": {
    "TBat": "26.31",
    "TDepCa": "35.44",
    "TDepFr": "27.73",
    "TM": "27.33",
    "TR": "unknown",
    "TS": "26.0",
    "TSR1": "unknown",
    "TSR2": "unknown",
    "TSSR": "28.67",
    "TT": "27.5",
    "TTub": "45.44"
  }
}
